__init__.py
__version__.py
analysis.py
main.py
models.py
print.py
targets.py
utils.py
validation.py
verbose.py
visualization.py
icons/404.png
icons/cidr.png
icons/fqdn.png
icons/ipv4.png
icons/target.png
icons/url.png
scopez-0.2.1.dist-info/licenses/LICENSE
scopez-0.2.1.dist-info/METADATA
scopez-0.2.1.dist-info/WHEEL
scopez-0.2.1.dist-info/entry_points.txt
scopez-0.2.1.dist-info/top_level.txt
scopez-0.2.1.dist-info/RECORD
