Metadata-Version: 2.4
Name: scopez
Version: 0.2.1
Summary: Scopez verifies connectivity to target servers, reveals CDN presence, and provides detailed target insights like reachability and RDAP.
Author-email: Christos Kaltsas <christos@xcalts.co>
Maintainer-email: Christos Kaltsas <christos@xcalts.co>
License: MIT License
Project-URL: Homepage, https://github.com/xcalts/scopez
Project-URL: Source, https://github.com/xcalts/scopez
Project-URL: Documentation, https://github.com/xcalts/scopez
Project-URL: Bug Reports, https://github.com/xcalts/scopez/issues
Project-URL: Changelog, https://github.com/xcalts/scopez/releases
Requires-Python: >3.11
License-File: LICENSE
Requires-Dist: Click
Requires-Dist: requests
Requires-Dist: rich
Requires-Dist: pydantic
Requires-Dist: ipwhois
Requires-Dist: fqdn
Requires-Dist: pandas
Requires-Dist: networkx
Requires-Dist: matplotlib
Requires-Dist: scipy
Dynamic: license-file
